README.md
setup.cfg
setup.py
AwsRds/__init__.py
AwsRds/aws_rds.py
careerskills.egg-info/PKG-INFO
careerskills.egg-info/SOURCES.txt
careerskills.egg-info/dependency_links.txt
careerskills.egg-info/requires.txt
careerskills.egg-info/top_level.txt
test/test_link_scraper.py