Metadata-Version: 1.0
Name: careerskills
Version: 0.1.1
Summary: A graphic user interface that allows you to find out the top desired transferable skills in your dream career; can be run in docker and upload results to AWS postgreSQL database
Home-page: https://github.com/YuyaR/linkedin-skill-miner.git
Author: Yuya Ra
Author-email: yuyacademia@gmail.com
License: agpl-3
Platform: UNKNOWN
